peewee_syncer/__init__.py
peewee_syncer/models.py
peewee_syncer/processor.py
peewee_syncer/utils.py
peewee_syncer-0.2.4.dist-info/METADATA
peewee_syncer-0.2.4.dist-info/WHEEL
peewee_syncer-0.2.4.dist-info/top_level.txt
peewee_syncer-0.2.4.dist-info/RECORD
