Metadata-Version: 2.1
Name: peewee-syncer
Version: 0.2.4
Summary: Tiny Sync tool using Peewee Models for persistance
Home-page: https://github.com/hampsterx/peewee-syncer
Author: Tim van der Hulst
Author-email: tim.vdh@gmail.com
License: Apache2
Platform: UNKNOWN
Classifier: Development Status :: 4 - Beta
Classifier: Intended Audience :: System Administrators
Classifier: License :: OSI Approved :: Apache Software License
Classifier: Programming Language :: Python :: 3
Requires-Dist: peewee (>=3.8.1)
Requires-Dist: python-dateutil (>=2.7.5)
Requires-Dist: backoff (>=1.8.0)
Provides-Extra: async
Requires-Dist: peewee-async (==0.6.0a0) ; extra == 'async'
Provides-Extra: async-mysql
Requires-Dist: peewee-asyn (==0.6.0a0) ; extra == 'async-mysql'
Requires-Dist: aiomysql (>=0.0.20) ; extra == 'async-mysql'
Provides-Extra: async-pg
Requires-Dist: peewee-asyn (==0.6.0a0) ; extra == 'async-pg'
Requires-Dist: aiopg (>=0.16.0) ; extra == 'async-pg'
